dkist_quality/__init__.py
dkist_quality/_version.py
dkist_quality/json_encoder.py
dkist_quality/report.py
dkist_quality/version.py
dkist_quality/fonts/Oswald-Bold.ttf
dkist_quality/fonts/Oswald-Regular.ttf
dkist_quality/tests/__init__.py
dkist_quality/tests/test_metric_models.py
dkist_quality/tests/test_report.py
dkist_quality-2.0.0.dist-info/licenses/LICENSE
dkist_quality-2.0.0.dist-info/METADATA
dkist_quality-2.0.0.dist-info/WHEEL
dkist_quality-2.0.0.dist-info/top_level.txt
dkist_quality-2.0.0.dist-info/RECORD
