Metadata-Version: 2.4
Name: dkist-quality
Version: 2.0.0
Summary: DKIST library for generating quality report pdf
Author-email: NSO / AURA <dkistdc@nso.edu>
License: MIT
Project-URL: repository, https://bitbucket.org/dkistdc/dkist-quality
Classifier: License :: OSI Approved :: MIT License
Classifier: Programming Language :: Python :: 3
Classifier: Programming Language :: Python :: 3.10
Classifier: Programming Language :: Python :: 3.11
Requires-Python: >=3.10
License-File: LICENSE
Requires-Dist: reportlab>=4.0.4
Requires-Dist: matplotlib>=3.8
Requires-Dist: seaborn>=0.13.0
Requires-Dist: dacite!=1.9.0,>=1.8.0
Requires-Dist: natsort>=8.0.0
Requires-Dist: pydantic>=2.0.0
Provides-Extra: test
Requires-Dist: tox>=4; extra == "test"
Requires-Dist: pypdf; extra == "test"
Requires-Dist: pytest; extra == "test"
Requires-Dist: pytest-cov; extra == "test"
Requires-Dist: Pygments; extra == "test"
Dynamic: license-file
